allphins/__init__.py
allphins/client/__init__.py
allphins/client/auth.py
allphins/client/client.py
allphins/client/result.py
allphins/const.py
allphins/interface.py
allphins/models/__init__.py
allphins/models/base.py
allphins/models/datasource.py
allphins/models/policy.py
allphins/models/portfolio.py
allphins/models/risk.py
allphins/models/scenario.py
allphins/models/scenario_list.py
allphins/singleton.py
allphins/status.py
allphins/utils.py
allphins_sdk-1.0.14.dist-info/METADATA
allphins_sdk-1.0.14.dist-info/WHEEL
allphins_sdk-1.0.14.dist-info/RECORD
